hebsafeharbor/__init__.py
hebsafeharbor/manager.py
hebsafeharbor/version.py
hebsafeharbor/anonymizer/__init__.py
hebsafeharbor/anonymizer/phi_anonymizer.py
hebsafeharbor/anonymizer/setting.py
hebsafeharbor/anonymizer/custom_operators/__init__.py
hebsafeharbor/anonymizer/custom_operators/birth_date_anonymizer_operator.py
hebsafeharbor/anonymizer/custom_operators/country_anonymizer_operator.py
hebsafeharbor/anonymizer/custom_operators/hebrew_replace_anonymizer_operator.py
hebsafeharbor/anonymizer/custom_operators/israeli_city_anonymizer_operator.py
hebsafeharbor/anonymizer/custom_operators/medical_date_anonymizer_operator.py
hebsafeharbor/common/__init__.py
hebsafeharbor/common/city_utils.py
hebsafeharbor/common/country_utils.py
hebsafeharbor/common/date_regex.py
hebsafeharbor/common/date_utils.py
hebsafeharbor/common/document.py
hebsafeharbor/common/prepositions.py
hebsafeharbor/common/terms_recognizer.py
hebsafeharbor/identifier/__init__.py
hebsafeharbor/identifier/heb_nlp_engine.py
hebsafeharbor/identifier/phi_identifier.py
hebsafeharbor/identifier/consolidation/__init__.py
hebsafeharbor/identifier/consolidation/conflict_handler.py
hebsafeharbor/identifier/consolidation/consolidation_config.py
hebsafeharbor/identifier/consolidation/consolidator.py
hebsafeharbor/identifier/consolidation/filter_entities.py
hebsafeharbor/identifier/consolidation/overlap_resolver.py
hebsafeharbor/identifier/consolidation/post_consolidation/__init__.py
hebsafeharbor/identifier/consolidation/post_consolidation/city_country_post_consolidator.py
hebsafeharbor/identifier/consolidation/post_consolidation/medical_post_consolidator.py
hebsafeharbor/identifier/consolidation/post_consolidation/post_consolidator_rule.py
hebsafeharbor/identifier/entity_smoother/__init__.py
hebsafeharbor/identifier/entity_smoother/entity_smoother_rule.py
hebsafeharbor/identifier/entity_smoother/entity_smoother_rule_executor.py
hebsafeharbor/identifier/entity_smoother/location_merger_rule.py
hebsafeharbor-0.1.1.dist-info/LICENSE
hebsafeharbor-0.1.1.dist-info/METADATA
hebsafeharbor-0.1.1.dist-info/WHEEL
hebsafeharbor-0.1.1.dist-info/top_level.txt
hebsafeharbor-0.1.1.dist-info/RECORD
