Metadata-Version: 2.1
Name: hebsafeharbor
Version: 0.1.1
Summary: De-identification toolkit for clinical text in Hebrew
Home-page: https://github.com/8400TheHealthNetwork/HebSafeHarbor
Author: hebsafeharbor
Author-email: hebsafeharbor@gmail.com
License: MIT License (MIT)
Keywords: hebrew nlp spacy SpaCy phi pii
Platform: UNKNOWN
Requires-Python: >=3.8.0
Requires-Dist: hebspacy
Requires-Dist: presidio-analyzer
Requires-Dist: presidio-anonymizer
Requires-Dist: pyahocorasick (==1.4.4)
